countest/__init__.py
countest/classifiers.py
countest-0.1.5.dist-info/LICENSE.txt
countest-0.1.5.dist-info/METADATA
countest-0.1.5.dist-info/WHEEL
countest-0.1.5.dist-info/top_level.txt
countest-0.1.5.dist-info/RECORD
