Metadata-Version: 2.1
Name: countest
Version: 0.1.5
Summary: CountEst is a module containing the implementation of count-based estimators, i.e., supervised learning algorithms that make predictions based on the frequency or count of specific events, categories, or values within a dataset.
Author: Sanskriti Singh, Alok Chauhan
Project-URL: Homepage, https://github.com/sanskriti-02/CountEst
Project-URL: Issues, https://github.com/sanskriti-02/CountEst/issues
Keywords: supervised learning,machine learning,count-based classifier
Classifier: Development Status :: 4 - Beta
Classifier: Intended Audience :: Developers
Classifier: Intended Audience :: Science/Research
Classifier: License :: OSI Approved :: BSD License
Classifier: Operating System :: MacOS
Classifier: Operating System :: Microsoft :: Windows
Classifier: Operating System :: POSIX
Classifier: Operating System :: Unix
Classifier: Programming Language :: Python
Classifier: Programming Language :: Python :: 3
Classifier: Programming Language :: Python :: 3.9
Classifier: Programming Language :: Python :: 3.10
Classifier: Programming Language :: Python :: 3.11
Classifier: Programming Language :: Python :: 3.12
Classifier: Programming Language :: Python :: 3.13
Classifier: Topic :: Scientific/Engineering
Classifier: Topic :: Software Development
Requires-Python: >=3.9
License-File: LICENSE.txt
Requires-Dist: numpy >=1.5
Requires-Dist: pandas >=1.1.5
Requires-Dist: scikit-learn >=0.20.0
